{
  "project_info": {
    "project_number": "1067175991077",
    "firebase_url": "https://mobile-android-hw8.firebaseio.com",
    "project_id": "mobile-android-hw8",
    "storage_bucket": "mobile-android-hw8.appspot.com"
  },
  "client": [
    {
      "client_info": {
        "mobilesdk_app_id": "1:1067175991077:android:b33e0b8bbe41d958b8accc",
        "android_client_info": {
          "package_name": "edu.gvsu.cis.convcalc"
        }
      },
      "oauth_client": [
        {
          "client_id": "1067175991077-fuq4b6e1rfb6if6sm4qj6ns698hgv0te.apps.googleusercontent.com",
          "client_type": 3
        }
      ],
      "api_key": [
        {
          "current_key": "AIzaSyAW3tbEo_AvsAXJCBallj8dnT_dvF1vhNw"
        }
      ],
      "services": {
        "appinvite_service": {
          "other_platform_oauth_client": [
            {
              "client_id": "1067175991077-fuq4b6e1rfb6if6sm4qj6ns698hgv0te.apps.googleusercontent.com",
              "client_type": 3
            }
          ]
        }
      }
    }
  ],
  "configuration_version": "1"
}